Metadata-Version: 2.1
Name: voicevox
Version: 0.0.6
Summary: Voicevox engine unoffical wrapper
Home-page: UNKNOWN
Author: tuna2134
License: MIT
Platform: UNKNOWN
License-File: LICENSE
